[
    {
        "title": "Cónclave de liderazgo de White Page",
        "date": " 07 SEPTIEMBRE 2023",
        "country": "Dubai, Emiratos Árabes Unidos",
        "dir": "white-page-leadership-conclave"
    },
    {
        "title": "TRADING LIVE AWARDS",
        "date": " 14 MAY 2023",
        "country": "Kuala Lumpur, Malasia",
        "dir": "ceremony"
    },
    {
        "title": "IRBID INVESTMENT & EXONOMIC CONFERENCE",
        "date": "08 MAY 2023",
        "country": "Irbid, Jordania",
        "dir": "irbid-investment-exonomic-conference"
    },
    {
        "title": "WEB 3.0",
        "date": " 12-13 MAR 2023",
        "country": "Ammán, Jordania",
        "dir": "web-3"
    }
]
